psgd_jax/.DS_Store
psgd_jax/__init__.py
psgd_jax/affine.py
psgd_jax/kron.py
psgd_jax/low_rank_approximation.py
psgd_jax/psgd_test.py
psgd_jax/utils.py
psgd_jax/xmat.py
psgd_jax-0.2.9.dist-info/LICENSE
psgd_jax-0.2.9.dist-info/WHEEL
psgd_jax-0.2.9.dist-info/METADATA
psgd_jax-0.2.9.dist-info/RECORD
