Metadata-Version: 2.3
Name: psgd-jax
Version: 0.2.9
Summary: An implementation of PSGD optimizer in JAX.
Keywords: python,machine learning,optimization,jax
Author: Evan Walters, Omead Pooladzandi, Xi-Lin Li
Requires-Python: >=3.9
Classifier: Environment :: Console
Classifier: Programming Language :: Python
Classifier: Intended Audience :: Developers
Classifier: Operating System :: OS Independent
Classifier: Programming Language :: Python :: 3
Classifier: Intended Audience :: Science/Research
Classifier: Development Status :: 4 - Beta
Classifier: Topic :: Scientific/Engineering :: Artificial Intelligence
Classifier: Topic :: Software Development :: Libraries :: Python Modules
Requires-Dist: numpy
Requires-Dist: matplotlib
Requires-Dist: jax
Requires-Dist: optax
Project-URL: homepage, https://github.com/evanatyourservice/psgd_jax
Project-URL: repository, https://github.com/evanatyourservice/psgd_jax
